.coveragerc
LICENSE
MANIFEST.in
Pipfile
Pipfile.lock
README.rst
requirements.txt
setup.cfg
setup.py
examples/README.rst
examples/convert_channel_coordframes.py
examples/label_anatomy_channels.py
seek_localize/__init__.py
seek_localize/bids.py
seek_localize/config.py
seek_localize/coordsystem.py
seek_localize/electrodes.py
seek_localize/io.py
seek_localize/label.py
seek_localize/localize.py
seek_localize.egg-info/PKG-INFO
seek_localize.egg-info/SOURCES.txt
seek_localize.egg-info/dependency_links.txt
seek_localize.egg-info/requires.txt
seek_localize.egg-info/top_level.txt
seek_localize/base/__init__.py
seek_localize/base/create_surface_files.py
seek_localize/base/tvb_utils.py
seek_localize/base/tvb_objects/__init__.py
seek_localize/base/tvb_objects/baseneuroimage.py
seek_localize/base/tvb_objects/dataset.py
seek_localize/base/tvb_objects/surface_object.py
seek_localize/contacts/__init__.py
seek_localize/contacts/electrode.py
seek_localize/contacts/neuroimage.py
seek_localize/templates/FreeSurferColorLUT.txt
seek_localize/utils/__init__.py
seek_localize/utils/freesurfer.py
seek_localize/utils/io.py
seek_localize/utils/projection.py
seek_localize/utils/space.py
seek_localize/utils/utils.py
tests/__init__.py
tests/conftest.py
tests/test_bids.py
tests/test_coordspace.py
tests/test_label.py
tests/test_localize.py
tests/test_utils.py
tests/dataset/test_label_cronedata.py