Metadata-Version: 1.2
Name: seek-localize
Version: 0.2.0
Summary: iEEG-BIDS anatomical and electrode coordinate interfacing software for easily generating anatomical interpretations of iEEG data.
Home-page: https://github.com/adam2302/seek_localize/
Author: ['Adam Li', 'Chester Huynh', 'Christopher Coogan']
License: GNU General Public License (GPL)
Project-URL: Documentation, https://github.com/adam2302/seek_localize/doc/
Project-URL: Source, https://github.com/adam2302/seek_localize/
Project-URL: Tracker, https://github.com/adam2302/seek_localize/issues
Platform: UNKNOWN
Classifier: Development Status :: 3 - Alpha
Classifier: Programming Language :: Python :: 3.7
Classifier: Programming Language :: Python :: 3.8
Classifier: Programming Language :: Python :: 3.9
Classifier: Programming Language :: Python :: Implementation
Classifier: Natural Language :: English
